mx_utils/__init__.py
mx_utils/_nbdev.py
mx_utils/common.py
mx_utils/core.py
mx_utils/data.py
mx_utils/gpu.py
mx_utils/img.py
mx_utils/libs.py
mx_utils/log.py
mx_utils/mem.py
mx_utils/vis.py
mx_utils-0.0.1.dist-info/LICENSE
mx_utils-0.0.1.dist-info/METADATA
mx_utils-0.0.1.dist-info/WHEEL
mx_utils-0.0.1.dist-info/entry_points.txt
mx_utils-0.0.1.dist-info/top_level.txt
mx_utils-0.0.1.dist-info/RECORD
