Metadata-Version: 2.1
Name: mx-utils
Version: 0.0.1
Summary: Utility scripts for softare development in data science.
Home-page: https://github.com/hallmx/mx_utils
Author: Mathew Hall
Author-email: mathew.hall100@gmail.com
License: Apache Software License 2.0
Keywords: data science software utilities nbdev python Colaboratory
Platform: UNKNOWN
Classifier: Development Status :: 3 - Alpha
Classifier: Intended Audience :: Developers
Classifier: License :: OSI Approved :: Apache Software License
Classifier: Natural Language :: English
Classifier: Programming Language :: Python :: 3.6
Classifier: Programming Language :: Python :: 3.7
Classifier: Programming Language :: Python :: 3.8
Requires-Python: >=3.6
